mkdocs_plugin_pills/__init__.py
mkdocs_plugin_pills/css/pills.css
mkdocs_plugin_pills/css/regex.svg
mkdocs_plugin_pills/css/unicode.svg
mkdocs_plugin_pills/plugin.py
mkdocs_plugin_pills/regex.py
mkdocs_plugin_pills/unicode.py
mkdocs_pills-0.1.0.dist-info/LICENSE.md
mkdocs_pills-0.1.0.dist-info/METADATA
mkdocs_pills-0.1.0.dist-info/WHEEL
mkdocs_pills-0.1.0.dist-info/entry_points.txt
mkdocs_pills-0.1.0.dist-info/RECORD
